AIConnector/__init__.py
AIConnector/session.py
AIConnector/common/__init__.py
AIConnector/common/exceptions.py
AIConnector/common/logger.py
AIConnector/common/message.py
AIConnector/common/network.py
AIConnector/connector/__init__.py
AIConnector/connector/azure_connector.py
AIConnector/connector/base_connector.py
AIConnector/connector/peer_connection_manager.py
AIConnector/connector/ws_connector.py
AIConnector/core/__init__.py
AIConnector/core/chat_client.py
AIConnector/core/job.py
AIConnector/core/job_manager.py
AIConnector/core/message_factory.py
AIConnector/discovery/__init__.py
AIConnector/discovery/azure_discovery_service.py
AIConnector/discovery/base_discovery_service.py
AIConnector/discovery/discovery_service.py
genai_protocol_lite-1.0.2.dist-info/licenses/LICENSE
genai_protocol_lite-1.0.2.dist-info/METADATA
genai_protocol_lite-1.0.2.dist-info/WHEEL
genai_protocol_lite-1.0.2.dist-info/top_level.txt
genai_protocol_lite-1.0.2.dist-info/RECORD
