Metadata-Version: 2.4
Name: genai-protocol-lite
Version: 1.0.2
Summary: GenAI Python project for direct agents connection either locally via websockets or remote via Azure Web PubSub
Home-page: https://github.com/genai-works-org/genai-protocol-lite
Author: Yaroslav Oliinyk, Yaroslav Motalov, Ivan Kuzlo, Pavlo Shyrinskykh
Author-email: pavlo.shyrinskykh@genai.works
License: Apache License 2.0
Classifier: Programming Language :: Python :: 3
Classifier: License :: OSI Approved :: MIT License
Classifier: Operating System :: OS Independent
Requires-Python: >=3.9
License-File: LICENSE
Requires-Dist: wcwidth==0.2.13
Requires-Dist: websockets~=15.0
Requires-Dist: colorlog==6.9.0
Requires-Dist: azure-messaging-webpubsubservice==1.2.1
Provides-Extra: dev
Requires-Dist: twine>=6.1.0; extra == "dev"
Dynamic: author
Dynamic: author-email
Dynamic: classifier
Dynamic: description
Dynamic: description-content-type
Dynamic: home-page
Dynamic: license
Dynamic: license-file
Dynamic: provides-extra
Dynamic: requires-dist
Dynamic: requires-python
Dynamic: summary
